ripiu/cmsplugin_columns/__init__.py
ripiu/cmsplugin_columns/apps.py
ripiu/cmsplugin_columns/cms_plugins.py
ripiu/cmsplugin_columns/models.py
ripiu/cmsplugin_columns/locale/it/.DS_Store
ripiu/cmsplugin_columns/locale/it/LC_MESSAGES/django.mo
ripiu/cmsplugin_columns/locale/it/LC_MESSAGES/django.po
ripiu/cmsplugin_columns/migrations/0001_initial.py
ripiu/cmsplugin_columns/migrations/0002_auto_20171003_1255.py
ripiu/cmsplugin_columns/migrations/__init__.py
ripiu/cmsplugin_columns/migrations/__pycache__/0001_initial.cpython-36.pyc
ripiu/cmsplugin_columns/migrations/__pycache__/0002_auto_20171003_1255.cpython-36.pyc
ripiu/cmsplugin_columns/migrations/__pycache__/__init__.cpython-36.pyc
ripiu/cmsplugin_columns/templates/ripiu/cmsplugin_columns/columns.html
ripiu.cmsplugin_columns-0.1.0.dist-info/DESCRIPTION.rst
ripiu.cmsplugin_columns-0.1.0.dist-info/METADATA
ripiu.cmsplugin_columns-0.1.0.dist-info/RECORD
ripiu.cmsplugin_columns-0.1.0.dist-info/WHEEL
ripiu.cmsplugin_columns-0.1.0.dist-info/metadata.json
ripiu.cmsplugin_columns-0.1.0.dist-info/top_level.txt
